{
  "Debug": true,
  "ListenPort": "8080",
  "Languages": {
    "ar": "阿拉伯语",
    "et": "爱沙尼亚语",
    "bg": "保加利亚语",
    "pl": "波兰语",
    "ko": "韩语",
    "bs-Latn": "波斯尼亚语",
    "fa": "波斯语",
    "mww": "白苗文",
    "da": "丹麦语",
    "de": "德语",
    "ru": "俄语",
    "fr": "法语",
    "fi": "芬兰语",
    "tlh-Qaak": "克林贡语(piqaD)",
    "tlh": "克林贡语",
    "hr": "克罗地亚语",
    "otq": "克雷塔罗奥托米语",
    "ca": "加泰隆语",
    "cs": "捷克语",
    "ro": "罗马尼亚语",
    "lv": "拉脱维亚语",
    "ht": "海地克里奥尔语",
    "lt": "立陶宛语",
    "zh-CHS": "中文"
  },
  "Accounts": [
    {
      
    }
  ]
}